{
    "states": {
        "Puducherry": {
            "heading": "The French-Indian Charm of Puducherry",
            "introduction": "Puducherry is a coastal union territory where French colonial elegance meets vibrant Tamil culture. With its charming boulevards, spiritual centers, and seaside tranquility, it offers a unique blend of European aesthetics and Indian traditions.",
            "coords": [
                11.9416,
                79.8083
            ],
            "zoom": 7,
            "sections": [
                {
                    "sectionTitle": "Colonial Heritage and Architecture",
                    "items": [
                        {
                            "id": "frenchquarter",
                            "title": "French Quarter",
                            "city": "Puducherry",
                            "coords": [
                                11.9369,
                                79.835
                            ],
                            "era": "Colonial Era",
                            "category": "Architecture",
                            "image": "images/Puducherry_frenchquarter.jpg",
                            "description": "The French Quarter is known for its colorful colonial buildings, tree-lined streets, and European-style cafes. It reflects Puducherry’s history as a French settlement. The area offers a charming blend of old-world elegance and modern culture.",
                            "articleLink": "https://www.google.com/search?q=French+Quarter+Puducherry"
                        },
                        {
                            "id": "auroville",
                            "title": "Auroville",
                            "city": "Auroville",
                            "coords": [
                                12.0067,
                                79.8103
                            ],
                            "era": "Modern Spiritual Community",
                            "category": "Spiritual Culture",
                            "image": "images/Puducherry_auroville.jpg",
                            "description": "Auroville is an experimental township founded on principles of peace, unity, and sustainable living. It attracts people from around the world seeking spiritual growth. The Matrimandir stands at its center as a symbol of meditation and harmony.",
                            "articleLink": "https://www.google.com/search?q=Auroville+Puducherry"
                        }
                    ]
                },
                {
                    "sectionTitle": "Beaches and Cultural Life",
                    "items": [
                        {
                            "id": "promenade",
                            "title": "Promenade Beach",
                            "city": "Puducherry",
                            "coords": [
                                11.9369,
                                79.8445
                            ],
                            "era": "Modern Cultural Space",
                            "category": "Nature",
                            "image": "images/Puducherry_promenade.jpg",
                            "description": "Promenade Beach is a popular seaside stretch known for its scenic views and relaxed atmosphere. It is lined with landmarks, cafes, and walking paths. The beach is central to Puducherry’s vibrant coastal life.",
                            "articleLink": "https://www.google.com/search?q=Promenade+Beach+Puducherry"
                        },
                        {
                            "id": "ashram",
                            "title": "Sri Aurobindo Ashram",
                            "city": "Puducherry",
                            "coords": [
                                11.934,
                                79.829
                            ],
                            "era": "20th Century Spiritual Movement",
                            "category": "Spiritual Culture",
                            "image": "images/Puducherry_ashram.jpg",
                            "description": "Sri Aurobindo Ashram is a spiritual community founded by Sri Aurobindo and The Mother. It is known for meditation, philosophy, and peaceful surroundings. The ashram attracts seekers from across the world.",
                            "articleLink": "https://www.google.com/search?q=Sri+Aurobindo+Ashram+Puducherry"
                        }
                    ]
                },
                {
                    "sectionTitle": "Cuisine and Language",
                    "items": [
                        {
                            "id": "fusion",
                            "title": "French-Tamil Cuisine",
                            "city": "Puducherry",
                            "coords": [
                                11.9416,
                                79.8083
                            ],
                            "era": "Colonial Fusion",
                            "category": "Cuisine",
                            "image": "images/Puducherry_fusion.jpg",
                            "description": "Puducherry’s cuisine is a unique blend of French and Tamil culinary traditions. From baguettes and pastries to spicy curries, the food reflects its colonial past. This fusion makes the city a culinary hotspot.",
                            "articleLink": "https://www.google.com/search?q=Puducherry+French+Tamil+cuisine"
                        },
                        {
                            "id": "languages",
                            "title": "Tamil, French, and English Languages",
                            "city": "Puducherry",
                            "coords": [
                                11.9416,
                                79.8083
                            ],
                            "era": "Modern Linguistic Blend",
                            "category": "Linguistics",
                            "image": "images/Puducherry_languages.jpg",
                            "description": "Tamil is the primary language spoken in Puducherry, alongside French and English due to its colonial history. This multilingual environment reflects the region’s cultural diversity. It enhances Puducherry’s global appeal.",
                            "articleLink": "https://www.google.com/search?q=Languages+in+Puducherry"
                        }
                    ]
                }
            ]
        }
    }
}